comparative_r_squared/__init__.py
comparative_r_squared/comparative_r_squared.py
tests/__init__.py
tests/test_comparative_r_squared.py
comparative_r_squared-0.1.dist-info/METADATA
comparative_r_squared-0.1.dist-info/WHEEL
comparative_r_squared-0.1.dist-info/top_level.txt
comparative_r_squared-0.1.dist-info/RECORD
